acclaim_badges/__init__.py
acclaim_badges/apps.py
acclaim_badges/contact.html
acclaim_badges/forms.py
acclaim_badges/models.py
acclaim_badges/urls.py
acclaim_badges/views.py
acclaim_badges/forms/badge_course.html
acclaim_badges/static/acclaim_badges/css/acclaim.css
acclaim_badges/static/acclaim_badges/img/acclaim_logo.gif
acclaim_badges/static/acclaim_badges/img/acclaim_logo.jpg
acclaim_badges/templates/acclaim_badges/acclaimtoken_confirm_delete.html
acclaim_badges/templates/acclaim_badges/acclaimtoken_form.html
acclaim_badges/templates/acclaim_badges/acclaimtoken_list.html
acclaim_badges/templates/acclaim_badges/acclaimtoken_update_form.html
acclaim_badges/templates/acclaim_badges/badgecourse_confirm_delete.html
acclaim_badges/templates/acclaim_badges/badgecourse_form.html
acclaim_badges/templates/acclaim_badges/badgecourse_list.html
acclaim_badges/templates/acclaim_badges/base.html
acclaim_badges-0.1.0.dist-info/DESCRIPTION.rst
acclaim_badges-0.1.0.dist-info/METADATA
acclaim_badges-0.1.0.dist-info/RECORD
acclaim_badges-0.1.0.dist-info/WHEEL
acclaim_badges-0.1.0.dist-info/metadata.json
acclaim_badges-0.1.0.dist-info/top_level.txt
