Metadata-Version: 2.0
Name: acclaim-badges
Version: 0.1.0
Summary: Acclaim Badges for EDX
Home-page: https://github.com/YourAcclaim/Acclaim-Badges-for-EDX
Author: Acclaim
Author-email: yancy.ribbens@gmail.com
License: UNKNOWN
Keywords: Django edx
Platform: UNKNOWN
Classifier: Development Status :: 3 - Alpha
Classifier: Framework :: Django
Classifier: Framework :: Django :: 1.8
Classifier: Framework :: Django :: 1.9
Classifier: Framework :: Django :: 1.10
Classifier: Intended Audience :: Developers
Classifier: License :: Other/Proprietary License
Classifier: Natural Language :: English
Classifier: Programming Language :: Python :: 2
Classifier: Programming Language :: Python :: 2.7
Classifier: Programming Language :: Python :: 3
Classifier: Programming Language :: Python :: 3.5
Requires-Dist: Django (>=1.8,<1.11)
Requires-Dist: django-encrypted-fields
Requires-Dist: django-model-utils (>=2.0)
